{
  "flight_number?": 1,
  "mission_name?": "FalconSat",
  "mission_id?": [],
  "upcoming?": false,
  "launch_year?": "2006",
  "launch_date_unix?": 1143239400,
  "launch_date_utc?": "2006-03-24T22:30:00.000Z",
  "launch_date_local?": "2006-03-25T10:30:00+12:00",
  "is_tentative?": false,
  "tentative_max_precision?": "hour",
  "tbd?": false,
  "launch_window?": 0,
  "rocket?": "$rocketModel",
  "ships?": [],
  "telemetry?": "$telemetryModel",
  "launch_site?": "$launchSiteModel",
  "launch_success?": false,
  "launch_failure_details?": "$launchFailureDetailsModel",
  "links?": "$linksModel",
  "details?": "Engine failure at 33 seconds and loss of vehicle",
  "static_fire_date_utc?": "2006-03-17T00:00:00.000Z",
  "static_fire_date_unix?": 1142553600,
  "timeline?": "$timelineModel",
  "crew?": []
}